{
  "users": [
    {
      "activities": [],
      "education": [
        {
          "name": "cmgdragon2222",
          "type": "titulo",
          "level": "grado",
          "university": "eeeeeeeeeeeeeeee",
          "finish_date": "12/12/1996"
        }
      ],
      "name": "cmgdragon",
      "email": "carlos_ole1996@hotmail.com",
      "surname": "aaaaaaaaaaaaaa",
      "type": "company",
      "password": "12345678",
      "id": 1,
      "profile": {
        "birthdate": "25/12/1996",
        "nationality": "es",
        "nif": "00000000T"
      }
    }
  ],
  "activities": [
    {
      "registered": [],
      "name": "cmgdragon2",
      "category": "enoturismo",
      "subcategory": "museovino",
      "language": "ca",
      "date": "12/12/1996",
      "price": "32",
      "user": 1,
      "id": 1
    },
    {
      "registered": [],
      "name": "asdsadada2222",
      "category": "enoturismo",
      "subcategory": "museovino",
      "language": "ca",
      "date": "12/12/1996",
      "price": "32",
      "user": 1,
      "id": 2
    }
  ]
}